Henson_Logging-0.6.0.dist-info/DESCRIPTION.rst
Henson_Logging-0.6.0.dist-info/METADATA
Henson_Logging-0.6.0.dist-info/RECORD
Henson_Logging-0.6.0.dist-info/WHEEL
Henson_Logging-0.6.0.dist-info/metadata.json
Henson_Logging-0.6.0.dist-info/top_level.txt
henson_logging/__init__.py
henson_logging/processors.py
