Metadata-Version: 2.0
Name: Henson-Logging
Version: 0.6.0
Summary: A library to use structured logging with a Henson application.
Home-page: https://henson-logging.readthedocs.io
Author: Andy Dirnberger, Jon Banafato, Leonard Bedner, Bo Guthrie, and others
Author-email: henson@iheart.com
License: Apache License, Version 2.0
Platform: UNKNOWN
Classifier: Development Status :: 4 - Beta
Classifier: Intended Audience :: Developers
Classifier: License :: OSI Approved :: Apache Software License
Classifier: Natural Language :: English
Classifier: Operating System :: POSIX
Classifier: Programming Language :: Python
Classifier: Programming Language :: Python :: 3.8
Classifier: Programming Language :: Python :: 3.9
Classifier: Programming Language :: Python :: 3 :: Only
Classifier: Topic :: Software Development :: Libraries :: Application Frameworks
Requires-Dist: Henson
Requires-Dist: structlog
